{"nodes": [{"id": "design_consently_design_system", "label": "Consently Design System", "file_type": "document", "source_file": "docs/Consently_DESIGN.md", "source_location": "line 1", "source_url": null, "captured_at": null, "author": null, "contributor": null}, {"id": "design_color_system", "label": "Color System (CSS Custom Properties)", "file_type": "document", "source_file": "docs/Consently_DESIGN.md", "source_location": "line 18", "source_url": null, "captured_at": null, "author": null, "contributor": null}, {"id": "design_trust_semantic_axis", "label": "Trust Semantic Axis (Blues \u2014 active consents)", "file_type": "document", "source_file": "docs/Consently_DESIGN.md", "source_location": "line 19", "source_url": null, "captured_at": null, "author": null, "contributor": null}, {"id": "design_risk_semantic_axis", "label": "Risk Semantic Axis (Amber/Red \u2014 attention required)", "file_type": "document", "source_file": "docs/Consently_DESIGN.md", "source_location": "line 19", "source_url": null, "captured_at": null, "author": null, "contributor": null}, {"id": "design_neutral_semantic_axis", "label": "Neutral Semantic Axis (Grays \u2014 structure and text)", "file_type": "document", "source_file": "docs/Consently_DESIGN.md", "source_location": "line 19", "source_url": null, "captured_at": null, "author": null, "contributor": null}, {"id": "design_data_type_color_coding", "label": "Data Type Color Coding (Airtable-inspired chips)", "file_type": "document", "source_file": "docs/Consently_DESIGN.md", "source_location": "line 113", "source_url": null, "captured_at": null, "author": null, "contributor": null}, {"id": "design_typography", "label": "Typography System (Inter + JetBrains Mono)", "file_type": "document", "source_file": "docs/Consently_DESIGN.md", "source_location": "line 129", "source_url": null, "captured_at": null, "author": null, "contributor": null}, {"id": "design_spacing_system", "label": "Spacing System (8px Base Grid)", "file_type": "document", "source_file": "docs/Consently_DESIGN.md", "source_location": "line 178", "source_url": null, "captured_at": null, "author": null, "contributor": null}, {"id": "design_border_radius", "label": "Border Radius Scale (sm:4px md:8px lg:12px xl:16px pill)", "file_type": "document", "source_file": "docs/Consently_DESIGN.md", "source_location": "line 209", "source_url": null, "captured_at": null, "author": null, "contributor": null}, {"id": "design_elevation_shadow", "label": "Elevation & Shadow System (sm, md, lg, focus)", "file_type": "document", "source_file": "docs/Consently_DESIGN.md", "source_location": "line 233", "source_url": null, "captured_at": null, "author": null, "contributor": null}, {"id": "design_service_card", "label": "Service Card Component (Risk-coded, Composio-inspired)", "file_type": "document", "source_file": "docs/Consently_DESIGN.md", "source_location": "line 257", "source_url": null, "captured_at": null, "author": null, "contributor": null}, {"id": "design_risk_badge", "label": "Risk Badge Component (Pill, HIGH/MEDIUM/LOW/REVOKED)", "file_type": "document", "source_file": "docs/Consently_DESIGN.md", "source_location": "line 290", "source_url": null, "captured_at": null, "author": null, "contributor": null}, {"id": "design_data_type_chip", "label": "Data Type Chip Component", "file_type": "document", "source_file": "docs/Consently_DESIGN.md", "source_location": "line 303", "source_url": null, "captured_at": null, "author": null, "contributor": null}, {"id": "design_buttons", "label": "Button Components (Primary / Danger / Ghost / Icon)", "file_type": "document", "source_file": "docs/Consently_DESIGN.md", "source_location": "line 315", "source_url": null, "captured_at": null, "author": null, "contributor": null}, {"id": "design_sidebar_navigation", "label": "Sidebar Navigation Component (Stratify-inspired)", "file_type": "document", "source_file": "docs/Consently_DESIGN.md", "source_location": "line 365", "source_url": null, "captured_at": null, "author": null, "contributor": null}, {"id": "design_summary_bar", "label": "Top Summary Bar Component", "file_type": "document", "source_file": "docs/Consently_DESIGN.md", "source_location": "line 397", "source_url": null, "captured_at": null, "author": null, "contributor": null}, {"id": "design_history_timeline_entry", "label": "Permission History Timeline Entry Component", "file_type": "document", "source_file": "docs/Consently_DESIGN.md", "source_location": "line 412", "source_url": null, "captured_at": null, "author": null, "contributor": null}, {"id": "design_revocation_modal", "label": "Revocation Confirmation Modal Component", "file_type": "document", "source_file": "docs/Consently_DESIGN.md", "source_location": "line 426", "source_url": null, "captured_at": null, "author": null, "contributor": null}, {"id": "design_layout_system", "label": "Layout System (Sidebar-fixed, Card Grid, Drawer)", "file_type": "document", "source_file": "docs/Consently_DESIGN.md", "source_location": "line 451", "source_url": null, "captured_at": null, "author": null, "contributor": null}, {"id": "design_detail_drawer", "label": "Detail Drawer Component (slides from right)", "file_type": "document", "source_file": "docs/Consently_DESIGN.md", "source_location": "line 474", "source_url": null, "captured_at": null, "author": null, "contributor": null}, {"id": "design_iconography", "label": "Iconography (Lucide React)", "file_type": "document", "source_file": "docs/Consently_DESIGN.md", "source_location": "line 499", "source_url": null, "captured_at": null, "author": null, "contributor": null}, {"id": "design_motion_animation", "label": "Motion & Animation System (revoke-shimmer, badge-pop, drawer-slide)", "file_type": "document", "source_file": "docs/Consently_DESIGN.md", "source_location": "line 531", "source_url": null, "captured_at": null, "author": null, "contributor": null}, {"id": "design_revoke_shimmer_animation", "label": "Revoke Shimmer Keyframe Animation", "file_type": "document", "source_file": "docs/Consently_DESIGN.md", "source_location": "line 549", "source_url": null, "captured_at": null, "author": null, "contributor": null}, {"id": "design_node_graph_vision", "label": "Node Graph Visualization (Full Vision, D3.js / React Flow)", "file_type": "document", "source_file": "docs/Consently_DESIGN.md", "source_location": "line 595", "source_url": null, "captured_at": null, "author": null, "contributor": null}, {"id": "design_card_grid", "label": "Card Grid Layout (Hackathon MVP Data Viz)", "file_type": "document", "source_file": "docs/Consently_DESIGN.md", "source_location": "line 588", "source_url": null, "captured_at": null, "author": null, "contributor": null}, {"id": "design_ux_copy_patterns", "label": "UX Copy Patterns (Plain-Language Consent Descriptions)", "file_type": "document", "source_file": "docs/Consently_DESIGN.md", "source_location": "line 605", "source_url": null, "captured_at": null, "author": null, "contributor": null}, {"id": "design_accessibility", "label": "Accessibility Guidelines (WCAG 2.1 AA, Focus States, ARIA)", "file_type": "document", "source_file": "docs/Consently_DESIGN.md", "source_location": "line 641", "source_url": null, "captured_at": null, "author": null, "contributor": null}, {"id": "design_component_file_structure", "label": "React Component File Structure (src/ layout)", "file_type": "document", "source_file": "docs/Consently_DESIGN.md", "source_location": "line 704", "source_url": null, "captured_at": null, "author": null, "contributor": null}, {"id": "design_tailwind_config", "label": "Tailwind CSS v4 CSS-First Setup (@theme tokens)", "file_type": "document", "source_file": "docs/Consently_DESIGN.md", "source_location": "line 667", "source_url": null, "captured_at": null, "author": null, "contributor": null}, {"id": "design_rationale_trust_first_not_scary", "label": "Rationale: Trust-First Design (Not a Security Tool that Feels Scary)", "file_type": "document", "source_file": "docs/Consently_DESIGN.md", "source_location": "line 10", "source_url": null, "captured_at": null, "author": null, "contributor": null}, {"id": "design_rationale_color_semantic_axes", "label": "Rationale: Three Semantic Color Axes (Trust, Risk, Neutral)", "file_type": "document", "source_file": "docs/Consently_DESIGN.md", "source_location": "line 19", "source_url": null, "captured_at": null, "author": null, "contributor": null}, {"id": "design_rationale_rounded_not_bubbly", "label": "Rationale: Rounded but Not Bubbly (Friendly Precision)", "file_type": "document", "source_file": "docs/Consently_DESIGN.md", "source_location": "line 211", "source_url": null, "captured_at": null, "author": null, "contributor": null}, {"id": "design_rationale_animation_purposeful", "label": "Rationale: Animation Communicates State Change, Not Decoration", "file_type": "document", "source_file": "docs/Consently_DESIGN.md", "source_location": "line 533", "source_url": null, "captured_at": null, "author": null, "contributor": null}, {"id": "design_rationale_light_mode_only", "label": "Rationale: Light Mode Only \u2014 Demo-safe, Projector-friendly", "file_type": "document", "source_file": "docs/Consently_DESIGN.md", "source_location": "line 13", "source_url": null, "captured_at": null, "author": null, "contributor": null}, {"id": "design_influence_airtable", "label": "Design Influence: Airtable (structured warmth)", "file_type": "document", "source_file": "docs/Consently_DESIGN.md", "source_location": "line 3", "source_url": null, "captured_at": null, "author": null, "contributor": null}, {"id": "design_influence_coinbase", "label": "Design Influence: Coinbase (institutional trust)", "file_type": "document", "source_file": "docs/Consently_DESIGN.md", "source_location": "line 3", "source_url": null, "captured_at": null, "author": null, "contributor": null}, {"id": "design_influence_composio", "label": "Design Influence: Composio (integration cards)", "file_type": "document", "source_file": "docs/Consently_DESIGN.md", "source_location": "line 3", "source_url": null, "captured_at": null, "author": null, "contributor": null}, {"id": "design_influence_stratify", "label": "Design Influence: Stratify (conversational dashboard shell)", "file_type": "document", "source_file": "docs/Consently_DESIGN.md", "source_location": "line 3", "source_url": null, "captured_at": null, "author": null, "contributor": null}], "edges": [{"source": "design_consently_design_system", "target": "prd_consently", "relation": "references", "confidence": "EXTRACTED", "confidence_score": 1.0, "source_file": "docs/Consently_DESIGN.md", "source_location": "line 1", "weight": 1.0}, {"source": "design_consently_design_system", "target": "design_color_system", "relation": "implements", "confidence": "EXTRACTED", "confidence_score": 1.0, "source_file": "docs/Consently_DESIGN.md", "source_location": "line 18", "weight": 1.0}, {"source": "design_consently_design_system", "target": "design_typography", "relation": "implements", "confidence": "EXTRACTED", "confidence_score": 1.0, "source_file": "docs/Consently_DESIGN.md", "source_location": "line 129", "weight": 1.0}, {"source": "design_consently_design_system", "target": "design_spacing_system", "relation": "implements", "confidence": "EXTRACTED", "confidence_score": 1.0, "source_file": "docs/Consently_DESIGN.md", "source_location": "line 178", "weight": 1.0}, {"source": "design_consently_design_system", "target": "design_border_radius", "relation": "implements", "confidence": "EXTRACTED", "confidence_score": 1.0, "source_file": "docs/Consently_DESIGN.md", "source_location": "line 209", "weight": 1.0}, {"source": "design_consently_design_system", "target": "design_elevation_shadow", "relation": "implements", "confidence": "EXTRACTED", "confidence_score": 1.0, "source_file": "docs/Consently_DESIGN.md", "source_location": "line 233", "weight": 1.0}, {"source": "design_consently_design_system", "target": "design_motion_animation", "relation": "implements", "confidence": "EXTRACTED", "confidence_score": 1.0, "source_file": "docs/Consently_DESIGN.md", "source_location": "line 531", "weight": 1.0}, {"source": "design_consently_design_system", "target": "design_accessibility", "relation": "implements", "confidence": "EXTRACTED", "confidence_score": 1.0, "source_file": "docs/Consently_DESIGN.md", "source_location": "line 641", "weight": 1.0}, {"source": "design_consently_design_system", "target": "design_influence_airtable", "relation": "references", "confidence": "EXTRACTED", "confidence_score": 1.0, "source_file": "docs/Consently_DESIGN.md", "source_location": "line 3", "weight": 1.0}, {"source": "design_consently_design_system", "target": "design_influence_coinbase", "relation": "references", "confidence": "EXTRACTED", "confidence_score": 1.0, "source_file": "docs/Consently_DESIGN.md", "source_location": "line 3", "weight": 1.0}, {"source": "design_consently_design_system", "target": "design_influence_composio", "relation": "references", "confidence": "EXTRACTED", "confidence_score": 1.0, "source_file": "docs/Consently_DESIGN.md", "source_location": "line 3", "weight": 1.0}, {"source": "design_consently_design_system", "target": "design_influence_stratify", "relation": "references", "confidence": "EXTRACTED", "confidence_score": 1.0, "source_file": "docs/Consently_DESIGN.md", "source_location": "line 3", "weight": 1.0}, {"source": "design_color_system", "target": "design_trust_semantic_axis", "relation": "implements", "confidence": "EXTRACTED", "confidence_score": 1.0, "source_file": "docs/Consently_DESIGN.md", "source_location": "line 19", "weight": 1.0}, {"source": "design_color_system", "target": "design_risk_semantic_axis", "relation": "implements", "confidence": "EXTRACTED", "confidence_score": 1.0, "source_file": "docs/Consently_DESIGN.md", "source_location": "line 19", "weight": 1.0}, {"source": "design_color_system", "target": "design_neutral_semantic_axis", "relation": "implements", "confidence": "EXTRACTED", "confidence_score": 1.0, "source_file": "docs/Consently_DESIGN.md", "source_location": "line 19", "weight": 1.0}, {"source": "design_color_system", "target": "design_data_type_color_coding", "relation": "implements", "confidence": "EXTRACTED", "confidence_score": 1.0, "source_file": "docs/Consently_DESIGN.md", "source_location": "line 113", "weight": 1.0}, {"source": "design_service_card", "target": "design_risk_badge", "relation": "references", "confidence": "EXTRACTED", "confidence_score": 1.0, "source_file": "docs/Consently_DESIGN.md", "source_location": "line 265", "weight": 1.0}, {"source": "design_service_card", "target": "design_data_type_chip", "relation": "references", "confidence": "EXTRACTED", "confidence_score": 1.0, "source_file": "docs/Consently_DESIGN.md", "source_location": "line 267", "weight": 1.0}, {"source": "design_service_card", "target": "design_buttons", "relation": "references", "confidence": "EXTRACTED", "confidence_score": 1.0, "source_file": "docs/Consently_DESIGN.md", "source_location": "line 271", "weight": 1.0}, {"source": "design_service_card", "target": "design_risk_semantic_axis", "relation": "conceptually_related_to", "confidence": "INFERRED", "confidence_score": 0.9, "source_file": "docs/Consently_DESIGN.md", "source_location": "line 284", "weight": 0.9}, {"source": "design_service_card", "target": "design_data_type_color_coding", "relation": "references", "confidence": "EXTRACTED", "confidence_score": 1.0, "source_file": "docs/Consently_DESIGN.md", "source_location": "line 267", "weight": 1.0}, {"source": "design_service_card", "target": "prd_consent_map_dashboard", "relation": "implements", "confidence": "EXTRACTED", "confidence_score": 1.0, "source_file": "docs/Consently_DESIGN.md", "source_location": "line 257", "weight": 1.0}, {"source": "design_layout_system", "target": "design_sidebar_navigation", "relation": "implements", "confidence": "EXTRACTED", "confidence_score": 1.0, "source_file": "docs/Consently_DESIGN.md", "source_location": "line 452", "weight": 1.0}, {"source": "design_layout_system", "target": "design_detail_drawer", "relation": "implements", "confidence": "EXTRACTED", "confidence_score": 1.0, "source_file": "docs/Consently_DESIGN.md", "source_location": "line 474", "weight": 1.0}, {"source": "design_layout_system", "target": "design_summary_bar", "relation": "implements", "confidence": "EXTRACTED", "confidence_score": 1.0, "source_file": "docs/Consently_DESIGN.md", "source_location": "line 397", "weight": 1.0}, {"source": "design_motion_animation", "target": "design_revoke_shimmer_animation", "relation": "implements", "confidence": "EXTRACTED", "confidence_score": 1.0, "source_file": "docs/Consently_DESIGN.md", "source_location": "line 549", "weight": 1.0}, {"source": "design_revoke_shimmer_animation", "target": "prd_one_click_revocation", "relation": "conceptually_related_to", "confidence": "INFERRED", "confidence_score": 0.95, "source_file": "docs/Consently_DESIGN.md", "source_location": "line 549", "weight": 0.95}, {"source": "design_revocation_modal", "target": "prd_one_click_revocation", "relation": "implements", "confidence": "EXTRACTED", "confidence_score": 1.0, "source_file": "docs/Consently_DESIGN.md", "source_location": "line 426", "weight": 1.0}, {"source": "design_history_timeline_entry", "target": "prd_permission_history_timeline", "relation": "implements", "confidence": "EXTRACTED", "confidence_score": 1.0, "source_file": "docs/Consently_DESIGN.md", "source_location": "line 412", "weight": 1.0}, {"source": "design_node_graph_vision", "target": "prd_cross_service_data_flow_viz", "relation": "implements", "confidence": "EXTRACTED", "confidence_score": 1.0, "source_file": "docs/Consently_DESIGN.md", "source_location": "line 595", "weight": 1.0}, {"source": "design_node_graph_vision", "target": "design_card_grid", "relation": "conceptually_related_to", "confidence": "EXTRACTED", "confidence_score": 1.0, "source_file": "docs/Consently_DESIGN.md", "source_location": "line 583", "weight": 1.0}, {"source": "design_card_grid", "target": "prd_hackathon_mvp", "relation": "conceptually_related_to", "confidence": "INFERRED", "confidence_score": 0.85, "source_file": "docs/Consently_DESIGN.md", "source_location": "line 588", "weight": 0.85}, {"source": "design_data_type_chip", "target": "design_data_type_color_coding", "relation": "implements", "confidence": "EXTRACTED", "confidence_score": 1.0, "source_file": "docs/Consently_DESIGN.md", "source_location": "line 303", "weight": 1.0}, {"source": "design_data_type_chip", "target": "prd_data_type_categorization", "relation": "implements", "confidence": "INFERRED", "confidence_score": 0.85, "source_file": "docs/Consently_DESIGN.md", "source_location": "line 303", "weight": 0.85}, {"source": "design_risk_badge", "target": "design_risk_semantic_axis", "relation": "implements", "confidence": "EXTRACTED", "confidence_score": 1.0, "source_file": "docs/Consently_DESIGN.md", "source_location": "line 290", "weight": 1.0}, {"source": "design_risk_badge", "target": "prd_risk_scoring_engine", "relation": "conceptually_related_to", "confidence": "INFERRED", "confidence_score": 0.75, "source_file": "docs/Consently_DESIGN.md", "source_location": "line 290", "weight": 0.75}, {"source": "design_ux_copy_patterns", "target": "prd_plain_language_ai_summaries", "relation": "semantically_similar_to", "confidence": "INFERRED", "confidence_score": 0.75, "source_file": "docs/Consently_DESIGN.md", "source_location": "line 605", "weight": 0.75}, {"source": "design_accessibility", "target": "design_risk_badge", "relation": "references", "confidence": "EXTRACTED", "confidence_score": 1.0, "source_file": "docs/Consently_DESIGN.md", "source_location": "line 645", "weight": 1.0}, {"source": "design_component_file_structure", "target": "design_service_card", "relation": "references", "confidence": "EXTRACTED", "confidence_score": 1.0, "source_file": "docs/Consently_DESIGN.md", "source_location": "line 713", "weight": 1.0}, {"source": "design_component_file_structure", "target": "design_history_timeline_entry", "relation": "references", "confidence": "EXTRACTED", "confidence_score": 1.0, "source_file": "docs/Consently_DESIGN.md", "source_location": "line 718", "weight": 1.0}, {"source": "design_component_file_structure", "target": "design_revocation_modal", "relation": "references", "confidence": "EXTRACTED", "confidence_score": 1.0, "source_file": "docs/Consently_DESIGN.md", "source_location": "line 715", "weight": 1.0}, {"source": "design_component_file_structure", "target": "design_sidebar_navigation", "relation": "references", "confidence": "EXTRACTED", "confidence_score": 1.0, "source_file": "docs/Consently_DESIGN.md", "source_location": "line 709", "weight": 1.0}, {"source": "design_tailwind_config", "target": "design_color_system", "relation": "implements", "confidence": "EXTRACTED", "confidence_score": 1.0, "source_file": "docs/Consently_DESIGN.md", "source_location": "line 667", "weight": 1.0}, {"source": "design_tailwind_config", "target": "design_typography", "relation": "implements", "confidence": "EXTRACTED", "confidence_score": 1.0, "source_file": "docs/Consently_DESIGN.md", "source_location": "line 685", "weight": 1.0}, {"source": "design_tailwind_config", "target": "design_border_radius", "relation": "implements", "confidence": "EXTRACTED", "confidence_score": 1.0, "source_file": "docs/Consently_DESIGN.md", "source_location": "line 689", "weight": 1.0}, {"source": "design_tailwind_config", "target": "design_elevation_shadow", "relation": "implements", "confidence": "EXTRACTED", "confidence_score": 1.0, "source_file": "docs/Consently_DESIGN.md", "source_location": "line 692", "weight": 1.0}, {"source": "design_rationale_trust_first_not_scary", "target": "design_consently_design_system", "relation": "rationale_for", "confidence": "EXTRACTED", "confidence_score": 1.0, "source_file": "docs/Consently_DESIGN.md", "source_location": "line 10", "weight": 1.0}, {"source": "design_rationale_color_semantic_axes", "target": "design_color_system", "relation": "rationale_for", "confidence": "EXTRACTED", "confidence_score": 1.0, "source_file": "docs/Consently_DESIGN.md", "source_location": "line 19", "weight": 1.0}, {"source": "design_rationale_rounded_not_bubbly", "target": "design_border_radius", "relation": "rationale_for", "confidence": "EXTRACTED", "confidence_score": 1.0, "source_file": "docs/Consently_DESIGN.md", "source_location": "line 211", "weight": 1.0}, {"source": "design_rationale_animation_purposeful", "target": "design_motion_animation", "relation": "rationale_for", "confidence": "EXTRACTED", "confidence_score": 1.0, "source_file": "docs/Consently_DESIGN.md", "source_location": "line 533", "weight": 1.0}, {"source": "design_rationale_light_mode_only", "target": "design_color_system", "relation": "rationale_for", "confidence": "EXTRACTED", "confidence_score": 1.0, "source_file": "docs/Consently_DESIGN.md", "source_location": "line 13", "weight": 1.0}], "hyperedges": [{"id": "service_card_design_token_system", "label": "Service Card Uses Risk Badge, Data Type Chip, Color Coding", "nodes": ["design_service_card", "design_risk_badge", "design_data_type_chip", "design_data_type_color_coding", "design_risk_semantic_axis"], "relation": "implement", "confidence": "EXTRACTED", "confidence_score": 1.0, "source_file": "docs/Consently_DESIGN.md"}, {"id": "consently_design_system_tokens", "label": "Consently Unified Design Token System", "nodes": ["design_color_system", "design_typography", "design_spacing_system", "design_border_radius", "design_elevation_shadow", "design_tailwind_config"], "relation": "form", "confidence": "EXTRACTED", "confidence_score": 1.0, "source_file": "docs/Consently_DESIGN.md"}]}